[{"mcsid":"463","from_user_id":"22","to_user_id":"1","message":"alright what about you?"},{"mcsid":"464","from_user_id":"1","to_user_id":"22","message":"i am ok here"},{"mcsid":"465","from_user_id":"22","to_user_id":"1","message":"ok.... it's good now"},{"mcsid":"466","from_user_id":"22","to_user_id":"1","message":" i hope. chatting :-)"},{"mcsid":"467","from_user_id":"1","to_user_id":"22","message":"yeah man looking good :D"},{"mcsid":"468","from_user_id":"1","to_user_id":"22","message":"i am happy"},{"mcsid":"469","from_user_id":"1","to_user_id":"22","message":"what the fuck is that?"},{"mcsid":"470","from_user_id":"1","to_user_id":"22","message":"o.hhh updating the myngl points i have :D"},{"mcsid":"471","from_user_id":"22","to_user_id":"1","message":"what baotu this?"}]